simple_prop_delay/simple.v
module Simple_Circuit_prop_delay (v, w, x, y, z);
  output y, z;
  input  v, w, x;
  wire   w2;

  and  #(30) G1 (w2, v, w);
  not  #(10) G2 (z, x);
  or   #(20) G3 (y, w2, z);
endmodule

simple_prop_delay/simple_tb.v
module t_Simple_Circuit_prop_delay;
  wire D, E;
  reg  A, B, C;

  Simple_Circuit_prop_delay M1 (A, B, C, D, E);

initial
  begin
    $dumpfile("wave.vcd");
    // $dumpvars(0, t_Simple_Circuit_prop_delay);
    $dumpvars(0, t_Simple_Circuit_prop_delay, Simple_circuit_prop_delay);
    A = 1'b0; B = 1'b0; C = 1'b0;
    #100 A = 1'b1; B = 1'b1; C = 1'b1;
    #50 A = 1'b0;
    #50 A = 1'b1; B = 1'b0;
  end

  initial #200 $finish;
endmodule

simple_prop_delay/wave_saved.vcd
$date
	Thu Sep  4 18:39:54 2025
$end
$version
	Icarus Verilog
$end
$timescale
	1s
$end
$scope module t_Simple_Circuit_prop_delay $end
$var wire 1 ! E $end
$var wire 1 " D $end
$var reg 1 # A $end
$var reg 1 $ B $end
$var reg 1 % C $end
$scope module M1 $end
$var wire 1 # v $end
$var wire 1 $ w $end
$var wire 1 & w2 $end
$var wire 1 % x $end
$var wire 1 " y $end
$var wire 1 ! z $end
$upscope $end
$upscope $end
$enddefinitions $end
#0
$dumpvars
x&
0%
0$
0#
x"
x!
$end
#10
1!
#30
1"
0&
#100
1%
1$
1#
#110
0!
#130
0"
1&
#150
1"
0#
#180
0&
#200
0"
0$
1#
